jeff_api/__init__.py
jeff_api/bridge.py
jeff_api/extension.py
jeff_api/message.py
jeff_api/tools.py
jeff_api-1.2.11.dist-info/LICENSE
jeff_api-1.2.11.dist-info/METADATA
jeff_api-1.2.11.dist-info/WHEEL
jeff_api-1.2.11.dist-info/top_level.txt
jeff_api-1.2.11.dist-info/RECORD
