Metadata-Version: 2.1
Name: jeff_api
Version: 1.2.11
Summary: A Python library for intercommunicating with Jeff.
Author-email: Mark CDA <aclo.create@gmail.com>
Project-URL: Homepage, https://github.com/markcda/jeff
Project-URL: Bug Tracker, https://github.com/markcda/jeff/issues
Classifier: Programming Language :: Python :: 3
Classifier: License :: OSI Approved :: MIT License
Classifier: Operating System :: OS Independent
Requires-Python: >=3.7
License-File: LICENSE
